odoo/addons/stock_picking_supplier_ref/README.rst
odoo/addons/stock_picking_supplier_ref/__init__.py
odoo/addons/stock_picking_supplier_ref/__manifest__.py
odoo/addons/stock_picking_supplier_ref/i18n/es.po
odoo/addons/stock_picking_supplier_ref/i18n/stock_picking_supplier_ref.pot
odoo/addons/stock_picking_supplier_ref/migrations/14.0.1.1.0/pre-migration.py
odoo/addons/stock_picking_supplier_ref/models/__init__.py
odoo/addons/stock_picking_supplier_ref/models/stock_picking.py
odoo/addons/stock_picking_supplier_ref/readme/CONTRIBUTORS.rst
odoo/addons/stock_picking_supplier_ref/readme/DESCRIPTION.rst
odoo/addons/stock_picking_supplier_ref/readme/HISTORY.rst
odoo/addons/stock_picking_supplier_ref/readme/USAGE.rst
odoo/addons/stock_picking_supplier_ref/static/description/icon.png
odoo/addons/stock_picking_supplier_ref/static/description/index.html
odoo/addons/stock_picking_supplier_ref/views/stock_picking.xml
odoo14_addon_stock_picking_supplier_ref-14.0.1.1.1.dist-info/METADATA
odoo14_addon_stock_picking_supplier_ref-14.0.1.1.1.dist-info/WHEEL
odoo14_addon_stock_picking_supplier_ref-14.0.1.1.1.dist-info/top_level.txt
odoo14_addon_stock_picking_supplier_ref-14.0.1.1.1.dist-info/RECORD
