Metadata-Version: 2.1
Name: odoo14-addon-stock-picking-supplier-ref
Version: 14.0.1.1.1
Summary: Adds a supplier reference field inside supplier's pickings and allows search for this reference.
Home-page: https://github.com/OCA/stock-logistics-workflow
Author: Trey, Odoo Community Association (OCA)
Author-email: support@odoo-community.org
License: AGPL-3
Platform: UNKNOWN
Classifier: Programming Language :: Python
Classifier: Framework :: Odoo
Classifier: Framework :: Odoo :: 14.0
Classifier: License :: OSI Approved :: GNU Affero General Public License v3
Requires-Python: >=3.6
Requires-Dist: odoo (<14.1dev,>=14.0a)
Requires-Dist: openupgradelib
